lqcodeAI/__init__.py
lqcodeAI/cli/__init__.py
lqcodeAI/cli/dynamic_cli.py
lqcodeAI/core/__init__.py
lqcodeAI/core/base.py
lqcodeAI/core/config.py
lqcodeAI/core/dynamic_ai.py
lqcodeAI/core/plugin_registry.py
lqcodeAI/plugins/__init__.py
lqcodeAI/plugins/ai_poetry.py
lqcodeAI/plugins/ai_snackprops.py
lqcodeAI/plugins/ai_weapons.py
lqcodeai-1.2.16.dist-info/licenses/LICENSE
lqcodeai-1.2.16.dist-info/METADATA
lqcodeai-1.2.16.dist-info/WHEEL
lqcodeai-1.2.16.dist-info/entry_points.txt
lqcodeai-1.2.16.dist-info/top_level.txt
lqcodeai-1.2.16.dist-info/RECORD
