Metadata-Version: 2.4
Name: lqcodeAI
Version: 1.2.16
Summary: 绿旗编程AI课程SDK
Home-page: https://github.com/TivonFeng/lqcode
Author: TivonFeng
Author-email: tivonfeng@163.com
Classifier: Programming Language :: Python :: 3
Classifier: License :: OSI Approved :: MIT License
Classifier: Operating System :: OS Independent
Requires-Python: >=3.6
License-File: LICENSE
Requires-Dist: requests>=2.25.1
Requires-Dist: cozepy>=0.13.1
Provides-Extra: streamlit
Requires-Dist: streamlit>=1.0.0; extra == "streamlit"
Dynamic: author
Dynamic: author-email
Dynamic: classifier
Dynamic: description
Dynamic: description-content-type
Dynamic: home-page
Dynamic: license-file
Dynamic: provides-extra
Dynamic: requires-dist
Dynamic: requires-python
Dynamic: summary
